marshmallow_objects/__init__.py
marshmallow_objects/models.py
marshmallow_objects-2.2.3.dist-info/AUTHORS
marshmallow_objects-2.2.3.dist-info/LICENSE
marshmallow_objects-2.2.3.dist-info/METADATA
marshmallow_objects-2.2.3.dist-info/WHEEL
marshmallow_objects-2.2.3.dist-info/pbr.json
marshmallow_objects-2.2.3.dist-info/top_level.txt
marshmallow_objects-2.2.3.dist-info/RECORD
