Metadata-Version: 2.1
Name: marshmallow-objects
Version: 2.2.3
Summary: Marshmallow Objects and Models
Home-page: https://github.com/sv-tools/marshmallow-objects
Author: Sergey Vilgelm
Author-email: sergey@vilgelm.info
License: MIT License
Keywords: marshmallow objects models yaml json ini config parser
Platform: UNKNOWN
Classifier: Intended Audience :: Information Technology
Classifier: Intended Audience :: Developers
Classifier: License :: OSI Approved :: MIT License
Classifier: Operating System :: OS Independent
Classifier: Programming Language :: Python
Classifier: Programming Language :: Python :: 3
Classifier: Topic :: Software Development :: Libraries :: Python Modules
Requires-Dist: marshmallow (>=3.0.0)
